ipyhc/__init__.py
ipyhc/__meta__.py
ipyhc/_config.py
ipyhc/build.py
ipyhc/builder_param.py
ipyhc/chart.py
ipyhc/display.py
ipyhc/ipyhc.json
ipyhc/sample.py
ipyhc/util.py
ipyhc/magics/__init__.py
ipyhc/magics/custom_magics.py
ipyhc/samples/df_bubble.csv
ipyhc/samples/df_heatmap.csv
ipyhc/samples/df_one_idx_one_col.csv
ipyhc/samples/df_one_idx_several_col.csv
ipyhc/samples/df_one_idx_several_col_2.csv
ipyhc/samples/df_one_idx_two_col.csv
ipyhc/samples/df_scatter.csv
ipyhc/samples/df_several_idx_one_col.csv
ipyhc/samples/df_several_idx_one_col_2.csv
ipyhc/samples/df_two_idx_one_col.csv
ipyhc/samples/df_two_idx_several_col.csv
ipyhc/static/extension.js
ipyhc/static/index.js
ipyhc/static/index.js.map
ipyhc-0.0.0a5.data/data/etc/jupyter/nbconfig/notebook.d/ipyhc.json
ipyhc-0.0.0a5.data/data/share/jupyter/nbextensions/ipyhc/extension.js
ipyhc-0.0.0a5.data/data/share/jupyter/nbextensions/ipyhc/index.js
ipyhc-0.0.0a5.data/data/share/jupyter/nbextensions/ipyhc/index.js.map
ipyhc-0.0.0a5.dist-info/METADATA
ipyhc-0.0.0a5.dist-info/RECORD
ipyhc-0.0.0a5.dist-info/WHEEL
ipyhc-0.0.0a5.dist-info/top_level.txt
