Metadata-Version: 2.1
Name: ipyhc
Version: 0.0.0a5
Summary: Jupyter widget - highcharts in the notebook
Home-page: https://gitlab.com/DGothrek/ipyhc
Author: DGothrek
Author-email: louisraison1@gmail.com
License: MIT
Download-URL: https://gitlab.com/DGothrek/ipyhc-dev/repository/archive.tar.gz?ref=0.0.0-alpha.5
Keywords: ipyhc,javascript,highcharts
Platform: UNKNOWN
Classifier: Development Status :: 4 - Beta
Classifier: License :: OSI Approved :: MIT License
Classifier: Programming Language :: Python :: 3.5
Classifier: Programming Language :: Python :: 3.6
Requires-Dist: ipywidgets (>=7.4.0)
Requires-Dist: pandas
Requires-Dist: simplejson
